xlsx_dict_reader/__init__.py
xlsx_dict_reader/dict_reader.py
xlsx_dict_reader-0.3.0.dist-info/LICENSE
xlsx_dict_reader-0.3.0.dist-info/METADATA
xlsx_dict_reader-0.3.0.dist-info/WHEEL
xlsx_dict_reader-0.3.0.dist-info/RECORD
