Metadata-Version: 2.1
Name: xlsx-dict-reader
Version: 0.3.0
Summary: An interface similar to csv.DictReader for openpyxl WorkSheet objects
Home-page: https://git.sr.ht/~tuxpup/xlsx-dict-reader
License: MIT
Author: Geoff Beier
Author-email: geoff@tuxpup.com
Requires-Python: >=3.10,<4.0
Classifier: License :: OSI Approved :: MIT License
Classifier: Programming Language :: Python :: 3
Classifier: Programming Language :: Python :: 3.10
Classifier: Programming Language :: Python :: 3.11
Classifier: Programming Language :: Python :: 3.12
Requires-Dist: openpyxl (>=3.1.2,<4.0.0)
Project-URL: Repository, https://git.sr.ht/~tuxpup/xlsx-dict-reader
